csv_schema_inference/__init__.py
csv_schema_inference/csv_schema_inference.py
csv_schema_inference-0.0.9.dist-info/LICENSE
csv_schema_inference-0.0.9.dist-info/METADATA
csv_schema_inference-0.0.9.dist-info/WHEEL
csv_schema_inference-0.0.9.dist-info/top_level.txt
csv_schema_inference-0.0.9.dist-info/RECORD
