Metadata-Version: 2.1
Name: csv-schema-inference
Version: 0.0.9
Summary: A tool to automatically infer columns data types in .csv files
Home-page: https://github.com/Wittline/csv-schema-inference
Author: Ramses Alexander Coraspe Valdez
Author-email: contacto@wittline.com
Classifier: Programming Language :: Python :: 3
Classifier: License :: OSI Approved :: MIT License
Classifier: Operating System :: OS Independent
Requires-Python: >=3.7
License-File: LICENSE
